mcp_neo4j_memory/__init__.py
mcp_neo4j_memory/neo4j_memory.py
mcp_neo4j_memory/server.py
mcp_neo4j_memory/utils.py
mcp_neo4j_temporal_substrate-0.6.1.dist-info/METADATA
mcp_neo4j_temporal_substrate-0.6.1.dist-info/WHEEL
mcp_neo4j_temporal_substrate-0.6.1.dist-info/entry_points.txt
mcp_neo4j_temporal_substrate-0.6.1.dist-info/RECORD
