Metadata-Version: 2.4
Name: mcp-neo4j-temporal-substrate
Version: 0.6.1
Summary: MCP Neo4j Memory Server for Temporal Substrate Evolution
Requires-Python: >=3.10
Requires-Dist: fastmcp>=2.0.0
Requires-Dist: neo4j>=5.26.0
Requires-Dist: pydantic>=2.10.1
Requires-Dist: starlette>=0.28.0
